db_conn/__init__.py
db_conn/database_access.py
db_conn/db_conn.py
db_conn-1.0.5.dist-info/LICENSE
db_conn-1.0.5.dist-info/METADATA
db_conn-1.0.5.dist-info/WHEEL
db_conn-1.0.5.dist-info/top_level.txt
db_conn-1.0.5.dist-info/RECORD
