Metadata-Version: 2.1
Name: db-conn
Version: 1.0.5
Summary: Database connection (Postgres, Redshift)
Home-page: https://github.com/oracy/db_conn
Author: Oracy Martos
Author-email: oramartos_21@hotmail.com
License: MIT
Platform: UNKNOWN
Classifier: License :: OSI Approved :: MIT License
Classifier: Development Status :: 4 - Beta
Classifier: Programming Language :: Python :: 3
Classifier: Programming Language :: Python :: 3.7
Classifier: Intended Audience :: Developers
Classifier: Topic :: Database
Classifier: Environment :: Console
Classifier: Operating System :: OS Independent
Requires-Dist: psycopg2
